TODO
ez_setup.py
setup.cfg
setup.py
Descriptive_Markup_Toolkit.egg-info/PKG-INFO
Descriptive_Markup_Toolkit.egg-info/SOURCES.txt
Descriptive_Markup_Toolkit.egg-info/dependency_links.txt
Descriptive_Markup_Toolkit.egg-info/not-zip-safe
Descriptive_Markup_Toolkit.egg-info/requires.txt
Descriptive_Markup_Toolkit.egg-info/top_level.txt
dmlt/__init__.py
dmlt/datastructure.py
dmlt/errors.py
dmlt/inode.py
dmlt/machine.py
dmlt/utils.py
dmlt/tests/__init__.py
dmlt/tests/test_utils.py
dmlt/tests/datastructure/__init__.py
dmlt/tests/datastructure/test_token_stack.py
dmlt/tests/datastructure/test_token_stream.py
dmlt/tests/datastructure/test_tokens.py
examples/simple/__init__.py
examples/simple/nodes.py
examples/simple/parser.py
scripts/count_loc.py
scripts/nosy.py
scripts/pylintrc
scripts/reindent.py