Metadata-Version: 1.0
Name: Descriptive-Markup-Toolkit
Version: 0.1
Summary: Just a nice small nice designed markup toolkit.
